azure/mgmt/appcontainers/__init__.py
azure/mgmt/appcontainers/_configuration.py
azure/mgmt/appcontainers/_container_apps_api_client.py
azure/mgmt/appcontainers/_patch.py
azure/mgmt/appcontainers/_version.py
azure/mgmt/appcontainers/py.typed
azure/mgmt/appcontainers/_utils/__init__.py
azure/mgmt/appcontainers/_utils/serialization.py
azure/mgmt/appcontainers/_utils/utils.py
azure/mgmt/appcontainers/aio/__init__.py
azure/mgmt/appcontainers/aio/_configuration.py
azure/mgmt/appcontainers/aio/_container_apps_api_client.py
azure/mgmt/appcontainers/aio/_patch.py
azure/mgmt/appcontainers/aio/operations/__init__.py
azure/mgmt/appcontainers/aio/operations/_available_workload_profiles_operations.py
azure/mgmt/appcontainers/aio/operations/_billing_meters_operations.py
azure/mgmt/appcontainers/aio/operations/_certificates_operations.py
azure/mgmt/appcontainers/aio/operations/_connected_environments_certificates_operations.py
azure/mgmt/appcontainers/aio/operations/_connected_environments_dapr_components_operations.py
azure/mgmt/appcontainers/aio/operations/_connected_environments_operations.py
azure/mgmt/appcontainers/aio/operations/_connected_environments_storages_operations.py
azure/mgmt/appcontainers/aio/operations/_container_apps_api_client_operations.py
azure/mgmt/appcontainers/aio/operations/_container_apps_auth_configs_operations.py
azure/mgmt/appcontainers/aio/operations/_container_apps_diagnostics_operations.py
azure/mgmt/appcontainers/aio/operations/_container_apps_operations.py
azure/mgmt/appcontainers/aio/operations/_container_apps_revision_replicas_operations.py
azure/mgmt/appcontainers/aio/operations/_container_apps_revisions_operations.py
azure/mgmt/appcontainers/aio/operations/_container_apps_session_pools_operations.py
azure/mgmt/appcontainers/aio/operations/_container_apps_source_controls_operations.py
azure/mgmt/appcontainers/aio/operations/_dapr_components_operations.py
azure/mgmt/appcontainers/aio/operations/_http_route_config_operations.py
azure_mgmt_appcontainers-4.0.0.dist-info/licenses/LICENSE
azure_mgmt_appcontainers-4.0.0.dist-info/METADATA
azure_mgmt_appcontainers-4.0.0.dist-info/WHEEL
azure_mgmt_appcontainers-4.0.0.dist-info/top_level.txt
azure_mgmt_appcontainers-4.0.0.dist-info/RECORD
